simpcli3/__init__.py
simpcli3/cli.py
simpcli3/docstring.py
simpcli3/logging.py
simpcli3-0.0.3.dist-info/LICENSE
simpcli3-0.0.3.dist-info/METADATA
simpcli3-0.0.3.dist-info/WHEEL
simpcli3-0.0.3.dist-info/entry_points.txt
simpcli3-0.0.3.dist-info/top_level.txt
simpcli3-0.0.3.dist-info/RECORD
