Metadata-Version: 2.1
Name: simpcli3
Version: 0.0.3
Summary: A Python3 library for turning functions into cmd-line programs trivially.
Home-page: https://github.com/haydenflinner/simpcli3
Author: Hayden Flinner
Author-email: haydenflinner@gmail.com
License: UNKNOWN
Keywords: cmd line command console argparse argparsing dataclass
Platform: UNKNOWN
Classifier: Intended Audience :: Information Technology
Classifier: Intended Audience :: Science/Research
Classifier: License :: OSI Approved :: BSD License
Classifier: Programming Language :: Python :: 3.7
Classifier: Programming Language :: Python :: 3.8
Requires-Python: >=3.7
Provides-Extra: dev
Requires-Dist: pytest ; extra == 'dev'
Requires-Dist: pytest-cov ; extra == 'dev'
Requires-Dist: pre-commit ; extra == 'dev'
Provides-Extra: test
Requires-Dist: pytest ; extra == 'test'
Requires-Dist: pytest-cov ; extra == 'test'
